{
	"info": {
		"_postman_id": "8645f526-aa9c-4d8a-bf74-5f81678d21e0",
		"name": "Proyecto8",
		"description": "Compraventa de tecnologia retro",
		"schema": "https://schema.getpostman.com/json/collection/v2.1.0/collection.json"
	},
	"item": [
		{
			"name": "Usuario",
			"item": [
				{
					"name": "Logaut",
					"event": [
						{
							"listen": "test",
							"script": {
								"exec": [
									"pm.globals.unset(\"accessToken\");"
								],
								"type": "text/javascript"
							}
						},
						{
							"listen": "prerequest",
							"script": {
								"exec": [
									""
								],
								"type": "text/javascript"
							}
						}
					],
					"request": {
						"method": "GET",
						"header": [],
						"url": {
							"raw": "http://localhost:8081/api/v1/proyecto8/usuarios/logout",
							"protocol": "http",
							"host": [
								"localhost"
							],
							"port": "8081",
							"path": [
								"api",
								"v1",
								"proyecto8",
								"usuarios",
								"logout"
							]
						}
					},
					"response": []
				},
				{
					"name": "Login",
					"event": [
						{
							"listen": "test",
							"script": {
								"exec": [
									"const response = pm.response.json();",
									"pm.globals.set(\"accessToken\",response.accessToken);"
								],
								"type": "text/javascript"
							}
						}
					],
					"request": {
						"method": "POST",
						"header": [
							{
								"key": "Authorization",
								"value": "",
								"type": "text",
								"disabled": true
							},
							{
								"key": "Authorization",
								"value": "",
								"type": "text",
								"disabled": true
							}
						],
						"body": {
							"mode": "raw",
							"raw": "{\n    \"email\": \"juansola@yopmail.com\",\n    \"contrasenha\": \"12345678\"\n}\n\n",
							"options": {
								"raw": {
									"language": "json"
								}
							}
						},
						"url": {
							"raw": "http://localhost:8081/api/v1/proyecto8/usuarios/login",
							"protocol": "http",
							"host": [
								"localhost"
							],
							"port": "8081",
							"path": [
								"api",
								"v1",
								"proyecto8",
								"usuarios",
								"login"
							]
						}
					},
					"response": []
				},
				{
					"name": "Registrar Usuario",
					"request": {
						"method": "POST",
						"header": [],
						"body": {
							"mode": "raw",
							"raw": "{\n    \"nombre\": \"miguel\",\n    \"apellidos\": \"visintíni\",\n    \"email\": \"miguelvidsdindtini5@yopmail.com\",\n    \"contrasenha\": \"12345678\",\n    \"repetirContrasenha\": \"12345678\",\n    \"nombreUsuario\": \"miguelviddsindtini6\",\n    \"localidad\": \"A Coruña\"\n}",
							"options": {
								"raw": {
									"language": "json"
								}
							}
						},
						"url": {
							"raw": "http://localhost:8081/api/v1/proyecto8/usuarios/registro",
							"protocol": "http",
							"host": [
								"localhost"
							],
							"port": "8081",
							"path": [
								"api",
								"v1",
								"proyecto8",
								"usuarios",
								"registro"
							]
						}
					},
					"response": []
				},
				{
					"name": "Actualizar usuario",
					"request": {
						"method": "PUT",
						"header": [
							{
								"key": "Authorization",
								"value": "Bearer {{accessToken}}",
								"type": "text"
							}
						],
						"body": {
							"mode": "raw",
							"raw": "{\n    \"nombre\": \"Pepe\",\n    \"apellidos\": \"Pacho\",\n    \"email\": \"pepepacho@yopmail.com\",\n    \"contrasenha\": \"12345678\",\n    \"repetirContrasenha\": \"12345678\",\n    \"nombreUsuario\": \"pepepacho\",\n    \"localidad\": \"A Coruña\"\n}",
							"options": {
								"raw": {
									"language": "json"
								}
							}
						},
						"url": {
							"raw": "http://localhost:8081/api/v1/proyecto8/usuarios/actualizar",
							"protocol": "http",
							"host": [
								"localhost"
							],
							"port": "8081",
							"path": [
								"api",
								"v1",
								"proyecto8",
								"usuarios",
								"actualizar"
							]
						}
					},
					"response": []
				},
				{
					"name": "Borar usuario",
					"request": {
						"method": "DELETE",
						"header": [
							{
								"key": "Authorization",
								"value": "Bearer {{accessToken}}",
								"type": "text"
							}
						],
						"url": {
							"raw": "http://localhost:8081/api/v1/proyecto8/usuarios/7",
							"protocol": "http",
							"host": [
								"localhost"
							],
							"port": "8081",
							"path": [
								"api",
								"v1",
								"proyecto8",
								"usuarios",
								"7"
							]
						}
					},
					"response": []
				},
				{
					"name": "Buscar articulos de usuario",
					"request": {
						"method": "GET",
						"header": [
							{
								"key": "Authorization",
								"value": "Bearer {{accessToken}}",
								"type": "text"
							}
						],
						"url": {
							"raw": "http://localhost:8081/api/v1/proyecto8/usuarios/6/articulos",
							"protocol": "http",
							"host": [
								"localhost"
							],
							"port": "8081",
							"path": [
								"api",
								"v1",
								"proyecto8",
								"usuarios",
								"6",
								"articulos"
							]
						}
					},
					"response": []
				},
				{
					"name": "Subir foto perfil",
					"request": {
						"method": "POST",
						"header": [
							{
								"key": "Authorization",
								"value": "Bearer {{accessToken}}",
								"type": "text"
							}
						],
						"body": {
							"mode": "formdata",
							"formdata": [
								{
									"key": "porfileImage",
									"type": "file",
									"src": "/home/hack45/Desktop/hack-a-boss/Back End/CarApp David/car-reviews-clase/public/images/profiles/14.jpeg"
								}
							]
						},
						"url": {
							"raw": "http://localhost:8081/api/v1/proyecto8/usuarios/subirImagen",
							"protocol": "http",
							"host": [
								"localhost"
							],
							"port": "8081",
							"path": [
								"api",
								"v1",
								"proyecto8",
								"usuarios",
								"subirImagen"
							]
						}
					},
					"response": []
				},
				{
					"name": "Buscar usuario por id",
					"request": {
						"method": "GET",
						"header": [
							{
								"key": "Authorization",
								"value": "Bearer {{accessToken}}",
								"type": "text"
							}
						],
						"url": {
							"raw": "http://localhost:8081/api/v1/proyecto8/usuarios/1",
							"protocol": "http",
							"host": [
								"localhost"
							],
							"port": "8081",
							"path": [
								"api",
								"v1",
								"proyecto8",
								"usuarios",
								"1"
							]
						}
					},
					"response": []
				}
			]
		},
		{
			"name": "Articulos",
			"item": [
				{
					"name": "Obtener articulos",
					"request": {
						"method": "GET",
						"header": [],
						"url": {
							"raw": "http://localhost:8081/api/v1/proyecto8/articulos",
							"protocol": "http",
							"host": [
								"localhost"
							],
							"port": "8081",
							"path": [
								"api",
								"v1",
								"proyecto8",
								"articulos"
							]
						}
					},
					"response": []
				},
				{
					"name": "Obtener Articulo por id",
					"request": {
						"method": "GET",
						"header": [],
						"url": {
							"raw": "http://localhost:8081/api/v1/proyecto8/articulos/3",
							"protocol": "http",
							"host": [
								"localhost"
							],
							"port": "8081",
							"path": [
								"api",
								"v1",
								"proyecto8",
								"articulos",
								"3"
							]
						}
					},
					"response": []
				},
				{
					"name": "Publicar articulo",
					"request": {
						"method": "POST",
						"header": [
							{
								"key": "Authorization",
								"value": "Bearer {{accessToken}}",
								"type": "text"
							}
						],
						"body": {
							"mode": "raw",
							"raw": "{\n    \"id_categoria\": 1,\n    \"titulo\": \"nintendo 64\",\n    \"descripcion\": \"Perfecto estado, con 5 juegos incluidos\",\n    \"localizacion\": \"A Coruña\",\n    \"precio\": 59\n}",
							"options": {
								"raw": {
									"language": "json"
								}
							}
						},
						"url": {
							"raw": "http://localhost:8081/api/v1/proyecto8/articulos",
							"protocol": "http",
							"host": [
								"localhost"
							],
							"port": "8081",
							"path": [
								"api",
								"v1",
								"proyecto8",
								"articulos"
							]
						}
					},
					"response": []
				},
				{
					"name": "Modificar articulo",
					"request": {
						"method": "PUT",
						"header": [
							{
								"key": "Authorization",
								"value": "Bearer {{accessToken}}",
								"type": "text"
							}
						],
						"body": {
							"mode": "raw",
							"raw": "{\n    \"id_categoria\":1,\n    \"titulo\":\"Nintendo\",\n    \"descripcion\":\"Nintendo buen estado\",\n    \"localizacion\":\"A Coruña\",\n    \"precio\": 5\n    }",
							"options": {
								"raw": {
									"language": "json"
								}
							}
						},
						"url": {
							"raw": "http://localhost:8081/api/v1/proyecto8/articulos/10",
							"protocol": "http",
							"host": [
								"localhost"
							],
							"port": "8081",
							"path": [
								"api",
								"v1",
								"proyecto8",
								"articulos",
								"10"
							]
						}
					},
					"response": []
				},
				{
					"name": "Borrar articulo",
					"request": {
						"method": "DELETE",
						"header": [
							{
								"key": "Authorization",
								"value": "Bearer {{accessToken}}",
								"type": "text"
							}
						],
						"url": {
							"raw": "http://localhost:8081/api/v1/proyecto8/articulos/10",
							"protocol": "http",
							"host": [
								"localhost"
							],
							"port": "8081",
							"path": [
								"api",
								"v1",
								"proyecto8",
								"articulos",
								"10"
							]
						}
					},
					"response": []
				},
				{
					"name": "Reservar articulo",
					"request": {
						"method": "PUT",
						"header": [
							{
								"key": "Authorization",
								"value": "Bearer {{accessToken}}",
								"type": "text"
							}
						],
						"body": {
							"mode": "raw",
							"raw": "{\"reservar\": 1}",
							"options": {
								"raw": {
									"language": "json"
								}
							}
						},
						"url": {
							"raw": "http://localhost:8081/api/v1/proyecto8/articulos/6/reservarArticulo",
							"protocol": "http",
							"host": [
								"localhost"
							],
							"port": "8081",
							"path": [
								"api",
								"v1",
								"proyecto8",
								"articulos",
								"6",
								"reservarArticulo"
							]
						}
					},
					"response": []
				},
				{
					"name": "Cancelar reserva",
					"request": {
						"method": "PUT",
						"header": [
							{
								"key": "Authorization",
								"value": "Bearer {{accessToken}}",
								"type": "text"
							}
						],
						"body": {
							"mode": "raw",
							"raw": "{\"anularReserva\": 1}",
							"options": {
								"raw": {
									"language": "json"
								}
							}
						},
						"url": {
							"raw": "http://localhost:8081/api/v1/proyecto8/articulos/6/borrarReserva",
							"protocol": "http",
							"host": [
								"localhost"
							],
							"port": "8081",
							"path": [
								"api",
								"v1",
								"proyecto8",
								"articulos",
								"6",
								"borrarReserva"
							]
						}
					},
					"response": []
				},
				{
					"name": "Confirmar Venta",
					"request": {
						"method": "PUT",
						"header": [
							{
								"key": "Authorization",
								"value": "Bearer {{accessToken}}",
								"type": "text"
							}
						],
						"body": {
							"mode": "raw",
							"raw": "{\"confirmarVenta\": 1}",
							"options": {
								"raw": {
									"language": "json"
								}
							}
						},
						"url": {
							"raw": "http://localhost:8081/api/v1/proyecto8/articulos/6/confirmarVenta",
							"protocol": "http",
							"host": [
								"localhost"
							],
							"port": "8081",
							"path": [
								"api",
								"v1",
								"proyecto8",
								"articulos",
								"6",
								"confirmarVenta"
							]
						}
					},
					"response": []
				},
				{
					"name": "Agrgar a Favoritos",
					"request": {
						"method": "POST",
						"header": [
							{
								"key": "Authorization",
								"value": "Bearer {{accessToken}}",
								"type": "text"
							}
						],
						"body": {
							"mode": "raw",
							"raw": "{\"agregarFav\": 1}",
							"options": {
								"raw": {
									"language": "json"
								}
							}
						},
						"url": {
							"raw": "http://localhost:8081/api/v1/proyecto8/articulos/6",
							"protocol": "http",
							"host": [
								"localhost"
							],
							"port": "8081",
							"path": [
								"api",
								"v1",
								"proyecto8",
								"articulos",
								"6"
							]
						}
					},
					"response": []
				},
				{
					"name": "Ver articulos por categoria",
					"request": {
						"method": "GET",
						"header": [],
						"url": {
							"raw": "http://localhost:8081/api/v1/proyecto8/articulos/categoria/8",
							"protocol": "http",
							"host": [
								"localhost"
							],
							"port": "8081",
							"path": [
								"api",
								"v1",
								"proyecto8",
								"articulos",
								"categoria",
								"8"
							]
						}
					},
					"response": []
				},
				{
					"name": "Resultado Busqueda",
					"protocolProfileBehavior": {
						"disableBodyPruning": true
					},
					"request": {
						"method": "GET",
						"header": [],
						"body": {
							"mode": "raw",
							"raw": "{\"palabrasClaves\": \"equipo nintendo\"}",
							"options": {
								"raw": {
									"language": "json"
								}
							}
						},
						"url": {
							"raw": "http://localhost:8081/api/v1/proyecto8/articulos/resultado/busqueda",
							"protocol": "http",
							"host": [
								"localhost"
							],
							"port": "8081",
							"path": [
								"api",
								"v1",
								"proyecto8",
								"articulos",
								"resultado",
								"busqueda"
							]
						}
					},
					"response": []
				}
			]
		},
		{
			"name": "Favoritos",
			"item": [
				{
					"name": "Obtener Articulos Favoritos",
					"request": {
						"method": "GET",
						"header": [
							{
								"key": "Authorization",
								"value": "Bearer {{accessToken}}",
								"type": "text"
							}
						],
						"url": {
							"raw": "http://localhost:8081/api/v1/proyecto8/articulosFav/",
							"protocol": "http",
							"host": [
								"localhost"
							],
							"port": "8081",
							"path": [
								"api",
								"v1",
								"proyecto8",
								"articulosFav",
								""
							]
						}
					},
					"response": []
				},
				{
					"name": "Borar articulo Favorito",
					"request": {
						"method": "DELETE",
						"header": [
							{
								"key": "Authorization",
								"value": "Bearer {{accessToken}}",
								"type": "text"
							}
						],
						"url": {
							"raw": "http://localhost:8081/api/v1/proyecto8/articulosFav/10",
							"protocol": "http",
							"host": [
								"localhost"
							],
							"port": "8081",
							"path": [
								"api",
								"v1",
								"proyecto8",
								"articulosFav",
								"10"
							]
						}
					},
					"response": []
				}
			]
		},
		{
			"name": "Ventas",
			"item": [
				{
					"name": "Mostrar ventas usuario",
					"request": {
						"method": "GET",
						"header": [
							{
								"key": "Authorization",
								"value": "Bearer {{accessToken}}",
								"type": "text"
							}
						],
						"url": {
							"raw": "http://localhost:8081/api/v1/proyecto8/ventas/ventas/1",
							"protocol": "http",
							"host": [
								"localhost"
							],
							"port": "8081",
							"path": [
								"api",
								"v1",
								"proyecto8",
								"ventas",
								"ventas",
								"1"
							]
						}
					},
					"response": []
				},
				{
					"name": "Mostrar compras usuario",
					"request": {
						"method": "GET",
						"header": [
							{
								"key": "Authorization",
								"value": "Bearer {{accessToken}}",
								"type": "text"
							}
						],
						"url": {
							"raw": "http://localhost:8081/api/v1/proyecto8/ventas/compras/1",
							"protocol": "http",
							"host": [
								"localhost"
							],
							"port": "8081",
							"path": [
								"api",
								"v1",
								"proyecto8",
								"ventas",
								"compras",
								"1"
							]
						}
					},
					"response": []
				},
				{
					"name": "Crear Valoracion",
					"request": {
						"method": "PUT",
						"header": [
							{
								"key": "Authorization",
								"value": "Bearer {{accessToken}}",
								"type": "text"
							}
						],
						"body": {
							"mode": "raw",
							"raw": "{\n    \"valoracion\": 5,\n    \"comentarioValoracion\": \"El ya me ha comprado un articulo a mi, y ahora yo le he comprado a el. Todo salio excelente\"\n}",
							"options": {
								"raw": {
									"language": "json"
								}
							}
						},
						"url": {
							"raw": "http://localhost:8081/api/v1/proyecto8/ventas/valoracion/3",
							"protocol": "http",
							"host": [
								"localhost"
							],
							"port": "8081",
							"path": [
								"api",
								"v1",
								"proyecto8",
								"ventas",
								"valoracion",
								"3"
							]
						}
					},
					"response": []
				},
				{
					"name": "Crear respuesta vendedor",
					"request": {
						"method": "PUT",
						"header": [
							{
								"key": "Authorization",
								"value": "Bearer {{accessToken}}",
								"type": "text"
							}
						],
						"body": {
							"mode": "raw",
							"raw": "{\n    \"respuesta\": \"Muchas gracias! un placer hacer negocios contigo! :)\"\n}",
							"options": {
								"raw": {
									"language": "json"
								}
							}
						},
						"url": {
							"raw": "http://localhost:8081/api/v1/proyecto8/ventas/respuesta/6",
							"protocol": "http",
							"host": [
								"localhost"
							],
							"port": "8081",
							"path": [
								"api",
								"v1",
								"proyecto8",
								"ventas",
								"respuesta",
								"6"
							]
						}
					},
					"response": []
				},
				{
					"name": "Ver valoraciones usuario",
					"request": {
						"method": "GET",
						"header": [
							{
								"key": "Authorization",
								"value": "Bearer {{accessToken}}",
								"type": "text"
							}
						],
						"url": {
							"raw": "http://localhost:8081/api/v1/proyecto8/ventas/verValoraciones/3",
							"protocol": "http",
							"host": [
								"localhost"
							],
							"port": "8081",
							"path": [
								"api",
								"v1",
								"proyecto8",
								"ventas",
								"verValoraciones",
								"3"
							]
						}
					},
					"response": []
				}
			]
		},
		{
			"name": "Fotos articulos",
			"item": [
				{
					"name": "Ver foto de articulo",
					"request": {
						"method": "GET",
						"header": [],
						"url": {
							"raw": "http://localhost:8081/api/v1/proyecto8/fotos/12",
							"protocol": "http",
							"host": [
								"localhost"
							],
							"port": "8081",
							"path": [
								"api",
								"v1",
								"proyecto8",
								"fotos",
								"12"
							]
						}
					},
					"response": []
				},
				{
					"name": "Subir imagen artículo",
					"request": {
						"method": "POST",
						"header": [
							{
								"key": "Authorization",
								"value": "Bearer {{accessToken}}",
								"type": "text"
							}
						],
						"body": {
							"mode": "formdata",
							"formdata": [
								{
									"key": "imagenArticulo",
									"type": "file",
									"src": [
										"/home/hack45/Desktop/14 (copy).jpeg",
										"/home/hack45/Desktop/14 (another copy).jpeg",
										"/home/hack45/Desktop/14 (5th copy).jpeg",
										"/home/hack45/Desktop/14 (4th copy).jpeg",
										"/home/hack45/Desktop/14 (3rd copy).jpeg",
										"/home/hack45/Desktop/14.jpeg"
									]
								}
							]
						},
						"url": {
							"raw": "http://localhost:8081/api/v1/proyecto8/fotos/subirImagen/12",
							"protocol": "http",
							"host": [
								"localhost"
							],
							"port": "8081",
							"path": [
								"api",
								"v1",
								"proyecto8",
								"fotos",
								"subirImagen",
								"12"
							]
						}
					},
					"response": []
				},
				{
					"name": "Borar imagen articulo",
					"request": {
						"method": "DELETE",
						"header": [
							{
								"key": "Authorization",
								"value": "Bearer {{accessToken}}",
								"type": "text"
							}
						],
						"url": {
							"raw": "http://localhost:8081/api/v1/proyecto8/fotos/borrarImagen/12",
							"protocol": "http",
							"host": [
								"localhost"
							],
							"port": "8081",
							"path": [
								"api",
								"v1",
								"proyecto8",
								"fotos",
								"borrarImagen",
								"12"
							]
						}
					},
					"response": []
				}
			]
		},
		{
			"name": "Mensajes",
			"item": [
				{
					"name": "Mostrar chats iniciados",
					"request": {
						"method": "GET",
						"header": [
							{
								"key": "Authorization",
								"value": "Bearer {{accessToken}}",
								"type": "text"
							}
						],
						"url": {
							"raw": "http://localhost:8081/api/v1/proyecto8/mensajes",
							"protocol": "http",
							"host": [
								"localhost"
							],
							"port": "8081",
							"path": [
								"api",
								"v1",
								"proyecto8",
								"mensajes"
							]
						}
					},
					"response": []
				},
				{
					"name": "Mostrar chat de articulo",
					"request": {
						"method": "GET",
						"header": [
							{
								"key": "Authorization",
								"value": "Bearer {{accessToken}}",
								"type": "text"
							}
						],
						"url": {
							"raw": "http://localhost:8081/api/v1/proyecto8/mensajes/10/1/3",
							"protocol": "http",
							"host": [
								"localhost"
							],
							"port": "8081",
							"path": [
								"api",
								"v1",
								"proyecto8",
								"mensajes",
								"10",
								"1",
								"3"
							]
						}
					},
					"response": []
				},
				{
					"name": "Insertar nuevo mensaje",
					"request": {
						"method": "POST",
						"header": [
							{
								"key": "Authorization",
								"value": "Bearer {{accessToken}}",
								"type": "text"
							}
						],
						"body": {
							"mode": "raw",
							"raw": "{\"mensaje\": \"perdon\"}",
							"options": {
								"raw": {
									"language": "json"
								}
							}
						},
						"url": {
							"raw": "http://localhost:8081/api/v1/proyecto8/mensajes/10/1/3",
							"protocol": "http",
							"host": [
								"localhost"
							],
							"port": "8081",
							"path": [
								"api",
								"v1",
								"proyecto8",
								"mensajes",
								"10",
								"1",
								"3"
							]
						}
					},
					"response": []
				}
			]
		}
	]
}